statistic/__init__.py
statistic/statistic.py
statistic-0.1.6.dist-info/LICENSE
statistic-0.1.6.dist-info/METADATA
statistic-0.1.6.dist-info/WHEEL
statistic-0.1.6.dist-info/top_level.txt
statistic-0.1.6.dist-info/RECORD
