Metadata-Version: 2.1
Name: statistic
Version: 0.1.6
Summary: projeto contendo varios metodos e funções estatisticos
Home-page: https://github.com/welitonsousa/statistic
Author: Weliton Sousa e Darice Sousa
Author-email: welitonubuntu@gmail.com
License: UNKNOWN
Project-URL: Bug Tracker, https://github.com/welitonsousa/statistic/issues
Platform: UNKNOWN
Classifier: Programming Language :: Python :: 3
Classifier: License :: OSI Approved :: MIT License
Classifier: Operating System :: OS Independent
Requires-Python: >=3.6
License-File: LICENSE
